buoy/__init__.py
buoy/base/__init__.py
buoy/base/database.py
buoy/base/data/__init__.py
buoy/base/data/item.py
buoy/base/data/nmea0183.py
buoy/base/data/utils.py
buoy/base/device/__init__.py
buoy/base/device/device.py
buoy/base/device/exceptions.py
buoy/base/device/threads/__init__.py
buoy/base/device/threads/base.py
buoy/base/device/threads/mqtt.py
buoy/base/device/threads/reader.py
buoy/base/device/threads/resender.py
buoy/base/device/threads/save.py
buoy/base/device/threads/writer.py
buoy/base/service/__init__.py
buoy/base/service/daemon.py
buoy/base/utils/__init__.py
buoy/base/utils/argsparse.py
buoy/base/utils/config.py
buoy/tests/__init__.py
buoy/tests/base_device_tests.py
buoy/tests/database.py
buoy/tests/item.py
buoy/tests/item_db_to_send_thread.py
buoy/tests/item_save_thread.py
buoy/tests/serial.py
tests/lib/__init__.py
tests/lib/data/__init__.py
tests/lib/data/test_data.py
tests/lib/database/__init__.py
tests/lib/database/test_db_save.py
tests/lib/device/__init__.py
tests/lib/device/test_device.py
tests/lib/device/test_device_reader_thread.py
tests/lib/device/test_item_db_to_send_thread.py
tests/lib/device/test_item_save_thread.py
tests/lib/device/test_item_send_thread.py
tests/lib/device/test_limbo.py
tests/lib/device/test_thread_base.py
tests/lib/service/__init__.py
tests/lib/service/test_daemon.py
tests/support/__init__.py
tests/support/function/__init__.py
Buoy_Base-0.0.11.dist-info/METADATA
Buoy_Base-0.0.11.dist-info/WHEEL
Buoy_Base-0.0.11.dist-info/entry_points.txt
Buoy_Base-0.0.11.dist-info/top_level.txt
Buoy_Base-0.0.11.dist-info/RECORD
