Metadata-Version: 2.1
Name: Buoy-Base
Version: 0.0.11
Summary: Library for developing IoT service
Home-page: https://gitlab.com/redmic-project/device/oag-buoy/buoy-lib
Author: Repositorio de Datos Marinos Integrados de Canarias
Author-email: info@redmic.es
License: MIT
Keywords: buoy ocean device iot
Platform: UNKNOWN
Classifier: Development Status :: 4 - Beta
Classifier: Intended Audience :: Developers
Classifier: Topic :: Software Development :: Build Tools
Classifier: License :: OSI Approved :: MIT License
Classifier: Programming Language :: Python :: 3.6
Requires-Dist: PyYAML
Requires-Dist: pyserial
Requires-Dist: python-dateutil
Requires-Dist: psycopg2
Requires-Dist: paho-mqtt
Provides-Extra: dev
Requires-Dist: check-manifest ; extra == 'dev'
Provides-Extra: test
Requires-Dist: coverage ; extra == 'test'
